{
  "": {
    "F612323246D1D0C649BD17AFA7C72509": "Activate Mix When Receiving From",
    "25896C8B42F80587FA506E80FDB0B1BB": "Activates mix on receiving a signal from the selected channel.",
    "5D1F0DBD499380FF2015FB9C96EA6746": "Adds the instigating player as a target for the Speaker to play audio from when activated.",
    "358CFB044206CA2D69A2859A8DF989AB": "Ambience",
    "2E57921B4E219DDB7AD61AB40F587E68": "Audio Mixer",
    "651A8DA742CF2AA193FF22B8A15FED33": "Audio Mixer",
    "22B4B7B941B0D5D95F5C18AAA679BF4E": "Control the mix of audio.",
    "2DA9D8F04FC97A628016CA9E70A8584E": "Control the mix of audio.",
    "A27F9D0443DC8EFC3D78E0AD4250FAF4": "Control the mix of audio.",
    "748F386D4482655441EB52AE16550087": "Deactivate Mix When Receiving From",
    "611DDFF44C3A30B4FDA63E87ACADE529": "Deactivates mix on receiving a signal from the selected channel.",
    "979956F14585E2F5EAE7559541B2DDBA": "Explosions",
    "A350D6DF41785826529E0EAFF35B96E9": "Footsteps",
    "C27EBAB249BA547E2C98089BE0B4D925": "Gadgets",
    "3A64E2774C9FE3FC16CB1185D40D95B0": "Impacts",
    "940BD78143FEC14D89D5BA8413F9A360": "Music",
    "0F5C295A47E5CA5186684FAE6176FD6A": "None",
    "63B3B13C4640A049BDED1882D8795BF0": "Register Player When Receiving From",
    "0BFD1636467269BC67075EA2F9E637E5": "Removes all instigating players as a target for the Speaker to play audio from when activated.",
    "B21402814646A4120B47B3BD344D0F0C": "Removes the instigating player as a target for the Speaker to play audio from when activated.",
    "7A34419E47C6DF3A99179FB497A50488": "SFX",
    "5C5B353743C55C431762DBBFE52AD69F": "Unregister All Players When Receiving From",
    "19FDE7F24BE3C637D16E9BBF97F0C5D9": "Unregister Player When Receiving From",
    "56335B4F4924EC53C77F69AEFF91A895": "Vehicle Engines",
    "ABA118C24DC2A79D2DB7E9BA25674DBD": "Vehicles",
    "7B5C5F3C400D2399863ECF87C8E3DE88": "Weapons"
  },
  "Fort.Actor.Building.Defaults": {
    "OptionDefinitionContainer.LabelOverride": "Label"
  },
  "UserOptionDefinition": {
    "Device_CRD_AudioMixer_C.Activate Mix.DisplayName": "Activate Mix",
    "Device_CRD_AudioMixer_C.bActivateInEditMode.DisplayName": "Activate in Edit Mode",
    "Device_CRD_AudioMixer_C.bActivateOnGameStart.DisplayName": "Activate on Game Start",
    "Device_CRD_AudioMixer_C.Activate Mix.Description": "Activates the mix associated with this mixer",
    "Device_CRD_AudioMixer_C.Bus.DisplayName": "Bus",
    "Device_CRD_AudioMixer_C.CanBeHeardBy.DisplayName": "Can be Heard By",
    "Device_CRD_AudioMixer_C.Deactivate Mix.DisplayName": "Deactivate Mix",
    "Device_CRD_AudioMixer_C.Deactivate Mix.Description": "Deactivates the mix associated with this mixer",
    "ECreativeRegisteredPlayerGroups.Everyone.DisplayName": "Everyone",
    "Device_CRD_AudioMixer_C.FaderValue.DisplayName": "Fader Value",
    "Device_CRD_AudioMixer_C.Mix.DisplayName": "Mix",
    "ECreativeRegisteredPlayerGroups.NonRegisteredPlayers.DisplayName": "Non Registered Players",
    "ECreativeRegisteredPlayerGroups.None.DisplayName": "None",
    "BoolMetaData.FalseDisplayName": "Off",
    "BoolMetaData.TrueDisplayName": "On",
    "Device_CRD_AudioMixer_C.Register Player.DisplayName": "Register Player",
    "ECreativeRegisteredPlayerGroups.RegisteredPlayers.DisplayName": "Registered Players",
    "Device_CRD_AudioMixer_C.Register Player.Description": "Registers a player, to be used in conjunction with the Can Be Heard By option",
    "Device_CRD_AudioMixer_C.Mix.Description": "The Mix that this device will activate / deactivate.",
    "Device_CRD_AudioMixer_C.CanBeHeardBy.Description": "This determines which players will experience the mix.",
    "Device_CRD_AudioMixer_C.Unregister All Players.DisplayName": "Unregister All Players",
    "Device_CRD_AudioMixer_C.Unregister Player.DisplayName": "Unregister Player",
    "Device_CRD_AudioMixer_C.Unregister Player.Description": "Unregisters a registered player, to be used in conjunction with the Can Be Heard By option",
    "Device_CRD_AudioMixer_C.Unregister All Players.Description": "Unregisters all registered players, to be used in conjunction with the Can Be Heard By option",
    "Device_CRD_AudioMixer_C.FaderValue.Description": "When a Mix isn't set, this is the value that the Bus above will be set to.",
    "Device_CRD_AudioMixer_C.Bus.Description": "When a Mix isn't set, we can assign a Bus here that will be used instead.",
    "Device_CRD_AudioMixer_C.bActivateInEditMode.Description": "When enabled, the mix will automatically activate in Edit Mode.",
    "Device_CRD_AudioMixer_C.bActivateOnGameStart.Description": "When enabled, the mix will automatically activate when the game starts."
  }
}