[
  {
    "Phoenix.VendingMachine.RarityWeights": {
      "InterpMode": {
        "Position": 58,
        "Value": 30
      },
      "Keys": {
        "Position": 99,
        "Value": [
          {
            "Position": 152,
            "Value": {
              "KeyTime": 0.0,
              "KeyValue": 100.0
            }
          },
          {
            "Position": 160,
            "Value": {
              "KeyTime": 1.0,
              "KeyValue": 0.0
            }
          },
          {
            "Position": 168,
            "Value": {
              "KeyTime": 9.0,
              "KeyValue": 0.0
            }
          }
        ]
      },
      "DefaultValue": {
        "Position": 201,
        "Value": 3.4028235E+38
      },
      "PreInfinityExtrap": {
        "Position": 238,
        "Value": 29
      },
      "PostInfinityExtrap": {
        "Position": 279,
        "Value": 29
      }
    },
    "Phoenix.VendingMachine.Cost.Ore": {
      "InterpMode": {
        "Position": 336,
        "Value": 30
      },
      "Keys": {
        "Position": 377,
        "Value": [
          {
            "Position": 430,
            "Value": {
              "KeyTime": 0.0,
              "KeyValue": 5.0
            }
          },
          {
            "Position": 438,
            "Value": {
              "KeyTime": 2.0,
              "KeyValue": 11.0
            }
          },
          {
            "Position": 446,
            "Value": {
              "KeyTime": 3.0,
              "KeyValue": 6.0
            }
          },
          {
            "Position": 454,
            "Value": {
              "KeyTime": 4.0,
              "KeyValue": 6.0
            }
          },
          {
            "Position": 462,
            "Value": {
              "KeyTime": 5.0,
              "KeyValue": 0.0
            }
          },
          {
            "Position": 470,
            "Value": {
              "KeyTime": 9.0,
              "KeyValue": 0.0
            }
          }
        ]
      },
      "DefaultValue": {
        "Position": 503,
        "Value": 3.4028235E+38
      },
      "PreInfinityExtrap": {
        "Position": 540,
        "Value": 29
      },
      "PostInfinityExtrap": {
        "Position": 581,
        "Value": 29
      }
    },
    "Phoenix.VendingMachine.Cost.Crystal": {
      "InterpMode": {
        "Position": 638,
        "Value": 30
      },
      "Keys": {
        "Position": 679,
        "Value": [
          {
            "Position": 732,
            "Value": {
              "KeyTime": 0.0,
              "KeyValue": 0.0
            }
          },
          {
            "Position": 740,
            "Value": {
              "KeyTime": 2.0,
              "KeyValue": 0.0
            }
          },
          {
            "Position": 748,
            "Value": {
              "KeyTime": 3.0,
              "KeyValue": 5.0
            }
          },
          {
            "Position": 756,
            "Value": {
              "KeyTime": 4.0,
              "KeyValue": 5.0
            }
          },
          {
            "Position": 764,
            "Value": {
              "KeyTime": 5.0,
              "KeyValue": 0.0
            }
          },
          {
            "Position": 772,
            "Value": {
              "KeyTime": 9.0,
              "KeyValue": 0.0
            }
          }
        ]
      },
      "DefaultValue": {
        "Position": 805,
        "Value": 3.4028235E+38
      },
      "PreInfinityExtrap": {
        "Position": 842,
        "Value": 29
      },
      "PostInfinityExtrap": {
        "Position": 883,
        "Value": 29
      }
    },
    "Phoenix.VendingMachine.Cost.Mechanism": {
      "InterpMode": {
        "Position": 940,
        "Value": 30
      },
      "Keys": {
        "Position": 981,
        "Value": [
          {
            "Position": 1034,
            "Value": {
              "KeyTime": 0.0,
              "KeyValue": 1.0
            }
          },
          {
            "Position": 1042,
            "Value": {
              "KeyTime": 1.0,
              "KeyValue": 3.0
            }
          },
          {
            "Position": 1050,
            "Value": {
              "KeyTime": 2.0,
              "KeyValue": 0.0
            }
          },
          {
            "Position": 1058,
            "Value": {
              "KeyTime": 9.0,
              "KeyValue": 0.0
            }
          }
        ]
      },
      "DefaultValue": {
        "Position": 1091,
        "Value": 3.4028235E+38
      },
      "PreInfinityExtrap": {
        "Position": 1128,
        "Value": 29
      },
      "PostInfinityExtrap": {
        "Position": 1169,
        "Value": 29
      }
    },
    "Phoenix.VendingMachine.Cost.PowerCell": {
      "InterpMode": {
        "Position": 1226,
        "Value": 30
      },
      "Keys": {
        "Position": 1267,
        "Value": [
          {
            "Position": 1320,
            "Value": {
              "KeyTime": 0.0,
              "KeyValue": 0.0
            }
          },
          {
            "Position": 1328,
            "Value": {
              "KeyTime": 1.0,
              "KeyValue": 0.0
            }
          },
          {
            "Position": 1336,
            "Value": {
              "KeyTime": 2.0,
              "KeyValue": 1.0
            }
          },
          {
            "Position": 1344,
            "Value": {
              "KeyTime": 4.0,
              "KeyValue": 1.0
            }
          },
          {
            "Position": 1352,
            "Value": {
              "KeyTime": 5.0,
              "KeyValue": 0.0
            }
          },
          {
            "Position": 1360,
            "Value": {
              "KeyTime": 9.0,
              "KeyValue": 0.0
            }
          }
        ]
      },
      "DefaultValue": {
        "Position": 1393,
        "Value": 3.4028235E+38
      },
      "PreInfinityExtrap": {
        "Position": 1430,
        "Value": 29
      },
      "PostInfinityExtrap": {
        "Position": 1471,
        "Value": 29
      }
    },
    "Phoenix.VendingMachine.CostTier": {
      "InterpMode": {
        "Position": 1528,
        "Value": 30
      },
      "Keys": {
        "Position": 1569,
        "Value": [
          {
            "Position": 1622,
            "Value": {
              "KeyTime": 0.0,
              "KeyValue": 1.0
            }
          },
          {
            "Position": 1630,
            "Value": {
              "KeyTime": 4.0,
              "KeyValue": 5.0
            }
          },
          {
            "Position": 1638,
            "Value": {
              "KeyTime": 5.0,
              "KeyValue": 0.0
            }
          },
          {
            "Position": 1646,
            "Value": {
              "KeyTime": 9.0,
              "KeyValue": 0.0
            }
          }
        ]
      },
      "DefaultValue": {
        "Position": 1679,
        "Value": 3.4028235E+38
      },
      "PreInfinityExtrap": {
        "Position": 1716,
        "Value": 29
      },
      "PostInfinityExtrap": {
        "Position": 1757,
        "Value": 29
      }
    },
    "Phoenix.VendingMachine.ItemCycleTime": {
      "InterpMode": {
        "Position": 1814,
        "Value": 30
      },
      "Keys": {
        "Position": 1855,
        "Value": [
          {
            "Position": 1908,
            "Value": {
              "KeyTime": 0.0,
              "KeyValue": 4.0
            }
          },
          {
            "Position": 1916,
            "Value": {
              "KeyTime": 1.0,
              "KeyValue": 0.0
            }
          },
          {
            "Position": 1924,
            "Value": {
              "KeyTime": 9.0,
              "KeyValue": 0.0
            }
          }
        ]
      },
      "DefaultValue": {
        "Position": 1957,
        "Value": 3.4028235E+38
      },
      "PreInfinityExtrap": {
        "Position": 1994,
        "Value": 29
      },
      "PostInfinityExtrap": {
        "Position": 2035,
        "Value": 29
      }
    },
    "Phoenix.VendingMachine.DropLootOnGroundBool": {
      "InterpMode": {
        "Position": 2092,
        "Value": 30
      },
      "Keys": {
        "Position": 2133,
        "Value": [
          {
            "Position": 2186,
            "Value": {
              "KeyTime": 0.0,
              "KeyValue": 0.0
            }
          },
          {
            "Position": 2194,
            "Value": {
              "KeyTime": 9.0,
              "KeyValue": 0.0
            }
          }
        ]
      },
      "DefaultValue": {
        "Position": 2227,
        "Value": 3.4028235E+38
      },
      "PreInfinityExtrap": {
        "Position": 2264,
        "Value": 29
      },
      "PostInfinityExtrap": {
        "Position": 2305,
        "Value": 29
      }
    },
    "Phoenix.VendingMachine.ItemsAreFree": {
      "InterpMode": {
        "Position": 2362,
        "Value": 30
      },
      "Keys": {
        "Position": 2403,
        "Value": [
          {
            "Position": 2456,
            "Value": {
              "KeyTime": 0.0,
              "KeyValue": 0.0
            }
          },
          {
            "Position": 2464,
            "Value": {
              "KeyTime": 9.0,
              "KeyValue": 0.0
            }
          }
        ]
      },
      "DefaultValue": {
        "Position": 2497,
        "Value": 3.4028235E+38
      },
      "PreInfinityExtrap": {
        "Position": 2534,
        "Value": 29
      },
      "PostInfinityExtrap": {
        "Position": 2575,
        "Value": 29
      }
    },
    "Phoenix.VendingMachine.MaxItemsToDrop": {
      "InterpMode": {
        "Position": 2632,
        "Value": 30
      },
      "Keys": {
        "Position": 2673,
        "Value": [
          {
            "Position": 2726,
            "Value": {
              "KeyTime": 0.0,
              "KeyValue": 1.0
            }
          },
          {
            "Position": 2734,
            "Value": {
              "KeyTime": 1.0,
              "KeyValue": 0.0
            }
          },
          {
            "Position": 2742,
            "Value": {
              "KeyTime": 9.0,
              "KeyValue": 0.0
            }
          }
        ]
      },
      "DefaultValue": {
        "Position": 2775,
        "Value": 3.4028235E+38
      },
      "PreInfinityExtrap": {
        "Position": 2812,
        "Value": 29
      },
      "PostInfinityExtrap": {
        "Position": 2853,
        "Value": 29
      }
    }
  }
]